neocode_ai/__init__.py
neocode_ai/_base_client.py
neocode_ai/_client.py
neocode_ai/_compat.py
neocode_ai/_constants.py
neocode_ai/_exceptions.py
neocode_ai/_files.py
neocode_ai/_models.py
neocode_ai/_qs.py
neocode_ai/_resource.py
neocode_ai/_response.py
neocode_ai/_streaming.py
neocode_ai/_types.py
neocode_ai/_version.py
neocode_ai/py.typed
neocode_ai/_utils/__init__.py
neocode_ai/_utils/_logs.py
neocode_ai/_utils/_proxy.py
neocode_ai/_utils/_reflection.py
neocode_ai/_utils/_resources_proxy.py
neocode_ai/_utils/_streams.py
neocode_ai/_utils/_sync.py
neocode_ai/_utils/_transform.py
neocode_ai/_utils/_typing.py
neocode_ai/_utils/_utils.py
neocode_ai/lib/.keep
neocode_ai/resources/__init__.py
neocode_ai/resources/app.py
neocode_ai/resources/config.py
neocode_ai/resources/event.py
neocode_ai/resources/file.py
neocode_ai/resources/find.py
neocode_ai/resources/session.py
neocode_ai/resources/tui.py
neocode_ai/types/__init__.py
neocode_ai/types/app.py
neocode_ai/types/app_init_response.py
neocode_ai/types/app_log_params.py
neocode_ai/types/app_log_response.py
neocode_ai/types/app_modes_response.py
neocode_ai/types/app_providers_response.py
neocode_ai/types/assistant_message.py
neocode_ai/types/config.py
neocode_ai/types/event_list_response.py
neocode_ai/types/file.py
neocode_ai/types/file_part.py
neocode_ai/types/file_part_input_param.py
neocode_ai/types/file_part_source.py
neocode_ai/types/file_part_source_param.py
neocode_ai/types/file_part_source_text.py
neocode_ai/types/file_part_source_text_param.py
neocode_ai/types/file_read_params.py
neocode_ai/types/file_read_response.py
neocode_ai/types/file_source.py
neocode_ai/types/file_source_param.py
neocode_ai/types/file_status_response.py
neocode_ai/types/find_files_params.py
neocode_ai/types/find_files_response.py
neocode_ai/types/find_symbols_params.py
neocode_ai/types/find_symbols_response.py
neocode_ai/types/find_text_params.py
neocode_ai/types/find_text_response.py
neocode_ai/types/keybinds_config.py
neocode_ai-0.1.0.dist-info/METADATA
neocode_ai-0.1.0.dist-info/WHEEL
neocode_ai-0.1.0.dist-info/licenses/LICENSE
neocode_ai-0.1.0.dist-info/RECORD
